my_first_package_nazmul/__init__.py
my_first_package_nazmul-0.0.2.dist-info/licenses/LICENSE
my_first_package_nazmul-0.0.2.dist-info/METADATA
my_first_package_nazmul-0.0.2.dist-info/WHEEL
my_first_package_nazmul-0.0.2.dist-info/top_level.txt
my_first_package_nazmul-0.0.2.dist-info/RECORD
